c2s2/standard/__init__.py
c2s2/standard/cluster.py
c2s2/standard/explain.py
c2s2/standard/io.py
c2s2/standard/load_hpo_graph.py
c2s2/standard/main.py
c2s2/standard/parse_phenopackets.py
c2s2/standard/perturb.py
c2s2/standard/test_cluster.py
c2s2/standard/test_explain.py
c2s2/standard/test_io.py
c2s2/standard/test_perturb.py
c2s2/standard/visualisations.py
c2s2/standard/test_data/README.md
c2s2/standard/test_data/bethlem-myopathy.json
c2s2/standard/test_data/example-cohort.json
c2s2/standard/test_data/hp.toy.json
c2s2_standard-0.2.0.dist-info/METADATA
c2s2_standard-0.2.0.dist-info/WHEEL
c2s2_standard-0.2.0.dist-info/top_level.txt
c2s2_standard-0.2.0.dist-info/RECORD
